mybasiccalculator/__init__.py
102003171_Calc-0.2.dist-info/LICENSE.txt
102003171_Calc-0.2.dist-info/METADATA
102003171_Calc-0.2.dist-info/WHEEL
102003171_Calc-0.2.dist-info/top_level.txt
102003171_Calc-0.2.dist-info/RECORD
