Metadata-Version: 2.1
Name: 102003171-Calc
Version: 0.2
Summary: This is a very basic calculator
Author: Manpreet Singh
Author-email: manpreetchahal0786@gmail.com
Classifier: Programming Language :: Python :: 3
Classifier: License :: OSI Approved :: MIT License
Classifier: Operating System :: OS Independent
License-File: LICENSE.txt
